MarkLib/__init__.py
MarkLib/builder.py
MarkLib/grader.py
MarkLib/markdata.py
MarkLib/task.py
MarkLib/taskitem.py
MarkLib/taskstage.py
MarkLib/models/__init__.py
MarkLib/models/base.py
MarkLib/models/condition.py
MarkLib-1.1.4.dist-info/LICENSE
MarkLib-1.1.4.dist-info/METADATA
MarkLib-1.1.4.dist-info/WHEEL
MarkLib-1.1.4.dist-info/top_level.txt
MarkLib-1.1.4.dist-info/RECORD
