Metadata-Version: 2.1
Name: MarkLib
Version: 1.1.4
Home-page: https://github.com/OGKG/PyMarkLib
Author: Vsevolod Hermaniuk & artandfi (Artem Fisunenko)
License: MIT
License-File: LICENSE
Requires-Dist: pydantic
